datasette_dns/__init__.py
datasette_dns-0.1a1.dist-info/METADATA
datasette_dns-0.1a1.dist-info/WHEEL
datasette_dns-0.1a1.dist-info/entry_points.txt
datasette_dns-0.1a1.dist-info/top_level.txt
datasette_dns-0.1a1.dist-info/RECORD
