Metadata-Version: 2.1
Name: datasette-dns
Version: 0.1a1
Summary: Custom SQL function for making DNS lookups
Home-page: https://github.com/simonw/datasette-dns
Author: Simon Willison
License: Apache License, Version 2.0
Project-URL: Issues, https://github.com/simonw/datasette-dns/issues
Project-URL: CI, https://github.com/simonw/datasette-dns/actions
Project-URL: Changelog, https://github.com/simonw/datasette-dns/releases
Platform: UNKNOWN
Requires-Dist: datasette
Requires-Dist: dnspython
Provides-Extra: test
Requires-Dist: pytest ; extra == 'test'
Requires-Dist: pytest-asyncio ; extra == 'test'
Requires-Dist: httpx ; extra == 'test'
Requires-Dist: pytest-mock ; extra == 'test'
